{
	"permissions": {
		"admin": 111111111111111111
	},
	"bot": {
		"token": "xxxxxxxxxxxxxxxxxxxxxxxxxxxxxxxxxxxxxxxxxxxxxxxxxxxxxxxxxxx",
		"description": "Hi, my name's Wojak, and I post pictures. Let's be frens. For any feedback, inquiries, suggestions, etc message @Strife#1407",
		"prefix": "?",
		"invite": "Your bot's invite link",
		"playing": "Wojak 1.0 | ?new_fren",
		"commands": {
			"info": [
				"help"
			],
			"hello": [
				"hi",
				"hey"
			],
			"wojak": [],
			"woblackjack": [
				"blackjack",
				"woblakjak",
				"blakjak"
			],
			"newfren": [],
			"_add": [],
			"_resetpool": [],
			"_remove": [],
			"_checkdb": [],
			"_shutdown": []
		}
	},
	"aws": {
		"region": "us-east-1",
		"wojak_image_bucket": "your-bucket-name",
		"money_db": "your-money-table-name"
	},
	"money": {
		"path": "WojaksLedger"
	},
	"greetings": [
		"Hello there, fren!",
		"Hi!",
		"Hey!",
		"'Sup!",
		"Yo!",
		"Waddup!",
		"Ayyy lmao"
	]
}